decord2-3.0.0.dist-info/RECORD
decord2-3.0.0.dist-info/WHEEL
decord2-3.0.0.dist-info/top_level.txt
decord2-3.0.0.dist-info/METADATA
decord/logging.py
decord/libdecord.dylib
decord/video_reader.py
decord/version.py
decord/video_loader.py
decord/_api_internal.py
decord/av_reader.py
decord/__init__.py
decord/ndarray.py
decord/audio_reader.py
decord/base.py
decord/bridge/tf.py
decord/bridge/mxnet.py
decord/bridge/torchdl.py
decord/bridge/__init__.py
decord/bridge/utils.py
decord/bridge/tvm.py
decord/function/__init__.py
decord/function/base.py
decord/_ffi/__init__.py
decord/_ffi/libinfo.py
decord/_ffi/ndarray.py
decord/_ffi/runtime_ctypes.py
decord/_ffi/base.py
decord/_ffi/function.py
decord/_ffi/_cy2/__init__.py
decord/_ffi/_cy3/__init__.py
decord/_ffi/_ctypes/__init__.py
decord/_ffi/_ctypes/types.py
decord/_ffi/_ctypes/ndarray.py
decord/_ffi/_ctypes/function.py
decord/.dylibs/libvorbisenc.2.dylib
decord/.dylibs/libSvtAv1Enc.3.1.0.dylib
decord/.dylibs/libdav1d.7.dylib
decord/.dylibs/libtwolame.0.dylib
decord/.dylibs/libx264.165.dylib
decord/.dylibs/libmp3lame.0.dylib
decord/.dylibs/libwebp.7.1.10.dylib
decord/.dylibs/libavcodec.62.11.100.dylib
decord/.dylibs/libopencore-amrnb.0.dylib
decord/.dylibs/libavformat.62.3.100.dylib
decord/.dylibs/libswresample.6.1.100.dylib
decord/.dylibs/libwebpmux.3.1.1.dylib
decord/.dylibs/libvpx.11.dylib
decord/.dylibs/libsharpyuv.0.1.1.dylib
decord/.dylibs/libvorbis.0.dylib
decord/.dylibs/libx265.215.dylib
decord/.dylibs/libopenh264.7.dylib
decord/.dylibs/libavdevice.62.1.100.dylib
decord/.dylibs/libavutil.60.8.100.dylib
decord/.dylibs/libspeex.1.dylib
decord/.dylibs/libswscale.9.1.100.dylib
decord/.dylibs/libopencore-amrwb.0.dylib
decord/.dylibs/libgmp.10.dylib
decord/.dylibs/libogg.0.dylib
decord/.dylibs/libavfilter.11.4.100.dylib
decord/.dylibs/libaom.3.11.0.dylib
decord/.dylibs/libopus.0.dylib
decord/data/__init__.py
decord/data/base_action.py
decord/data/dataloader.py
decord/data/kinetics/__init__.py
decord/data/kinetics/kinetics400_action.py
decord/data/transforms/__init__.py
