Metadata-Version: 2.4
Name: decord2
Version: 3.0.0
Summary: Decord2 is a high-performance, efficient video decoding and loading library for deep learning research, featuring smart shuffling, random frame access, GPU acceleration, and seamless integration with popular frameworks.
Home-page: https://github.com/johnnynunez/decord2
Author-email: Johnny Núñez <johnnynunez@ub.edu>
Maintainer: Decord committers
Maintainer-email: Johnny Núñez <johnnynunez@ub.edu>
License: Apache-2.0
Keywords: python,video,loader,deep learning
Requires-Python: >=3.9.0
Requires-Dist: numpy>=1.26.4
Dynamic: home-page
Dynamic: maintainer
Dynamic: requires-python
